[
  {
    "id": "beer_1",
    "name": "生ビール（大）",
    "カテゴリ": "ビール",
    "価格": 500,
    "説明": ""
  },
  {
    "id": "beer_2",
    "name": "生ビール（中）",
    "カテゴリ": "ビール",
    "価格": 480,
    "説明": ""
  },
  {
    "id": "beer_3",
    "name": "生ビール（グラス）",
    "カテゴリ": "ビール",
    "価格": 380,
    "説明": ""
  },
  {
    "id": "beer_4",
    "name": "瓶ビール（中瓶）",
    "カテゴリ": "ビール",
    "価格": 530,
    "説明": ""
  },
  {
    "id": "beer_5",
    "name": "ノンアルコール",
    "カテゴリ": "ビール",
    "価格": 380,
    "説明": ""
  },
  {
    "id": "hoppy_1",
    "name": "ホッピーセット（白・黒）",
    "カテゴリ": "ホッピー",
    "価格": 430,
    "説明": ""
  },
  {
    "id": "hoppy_2",
    "name": "ホッピー（外）",
    "カテゴリ": "ホッピー",
    "価格": 270,
    "説明": ""
  },
  {
    "id": "hoppy_3",
    "name": "ホッピー（中）",
    "カテゴリ": "ホッピー",
    "価格": 200,
    "説明": ""
  },
  {
    "id": "hoppy_4",
    "name": "ラムラムッピー",
    "カテゴリ": "ホッピー",
    "価格": 480,
    "説明": ""
  },
  {
    "id": "hoppy_5",
    "name": "ラム（中）",
    "カテゴリ": "ホッピー",
    "価格": 250,
    "説明": ""
  },
  {
    "id": "chuhai_sour_1",
    "name": "バイス",
    "カテゴリ": "酎ハイ＆サワー",
    "価格": 430,
    "説明": ""
  },
  {
    "id": "chuhai_sour_2",
    "name": "クエン酸サワー",
    "カテゴリ": "酎ハイ＆サワー",
    "価格": 400,
    "説明": ""
  },
  {
    "id": "chuhai_sour_3",
    "name": "金魚サワー＆金魚割",
    "カテゴリ": "酎ハイ＆サワー",
    "価格": 430,
    "説明": ""
  },
  {
    "id": "chuhai_sour_4",
    "name": "濃い緑茶割",
    "カテゴリ": "酎ハイ＆サワー",
    "価格": 430,
    "説明": ""
  },
  {
    "id": "chuhai_sour_5",
    "name": "ウーロンハイ",
    "カテゴリ": "酎ハイ＆サワー",
    "価格": 370,
    "説明": ""
  },
  {
    "id": "chuhai_sour_6",
    "name": "レッズハイ",
    "カテゴリ": "酎ハイ＆サワー",
    "価格": 470,
    "説明": ""
  },
  {
    "id": "chuhai_sour_7",
    "name": "チューハイサワー",
    "カテゴリ": "酎ハイ＆サワー",
    "価格": 370,
    "説明": ""
  },
  {
    "id": "chuhai_sour_8",
    "name": "レモンサワー",
    "カテゴリ": "酎ハイ＆サワー",
    "価格": 370,
    "説明": ""
  },
  {
    "id": "chuhai_sour_9",
    "name": "プレミアムレモンサワー",
    "カテゴリ": "酎ハイ＆サワー",
    "価格": 570,
    "説明": ""
  },
  {
    "id": "chuhai_sour_10",
    "name": "ライムサワー",
    "カテゴリ": "酎ハイ＆サワー",
    "価格": 370,
    "説明": ""
  },
  {
    "id": "chuhai_sour_11",
    "name": "青りんごサワー",
    "カテゴリ": "酎ハイ＆サワー",
    "価格": 370,
    "説明": ""
  },
  {
    "id": "chuhai_sour_12",
    "name": "巨峰サワー",
    "カテゴリ": "酎ハイ＆サワー",
    "価格": 370,
    "説明": ""
  },
  {
    "id": "chuhai_sour_13",
    "name": "梅サワー",
    "カテゴリ": "酎ハイ＆サワー",
    "価格": 370,
    "説明": ""
  },
  {
    "id": "chuhai_sour_14",
    "name": "梅干しサワー",
    "カテゴリ": "酎ハイ＆サワー",
    "価格": 470,
    "説明": ""
  },
  {
    "id": "chuhai_sour_15",
    "name": "カシスサワー",
    "カテゴリ": "酎ハイ＆サワー",
    "価格": 370,
    "説明": ""
  },
  {
    "id": "chuhai_sour_16",
    "name": "シークアーサーサワー",
    "カテゴリ": "酎ハイ＆サワー",
    "価格": 370,
    "説明": ""
  },
  {
    "id": "chuhai_sour_17",
    "name": "生グレープフルーツサワー",
    "カテゴリ": "酎ハイ＆サワー",
    "価格": 470,
    "説明": ""
  },
  {
    "id": "honkaku_shochu_1",
    "name": "白（右下の棚）（麦・米・芋）",
    "カテゴリ": "本格焼酎",
    "価格": 380,
    "説明": ""
  },
  {
    "id": "premium_shochu_1",
    "name": "伊佐美",
    "カテゴリ": "プレミアム焼酎",
    "価格": 680,
    "説明": ""
  },
  {
    "id": "premium_shochu_2",
    "name": "元老院",
    "カテゴリ": "プレミアム焼酎",
    "価格": 680,
    "説明": ""
  },
  {
    "id": "premium_shochu_3",
    "name": "宝山（富乃・吉兆・白天）",
    "カテゴリ": "プレミアム焼酎",
    "価格": 680,
    "説明": ""
  },
  {
    "id": "premium_shochu_4",
    "name": "なかむら",
    "カテゴリ": "プレミアム焼酎",
    "価格": 680,
    "説明": ""
  },
  {
    "id": "premium_shochu_5",
    "name": "川越",
    "カテゴリ": "プレミアム焼酎",
    "価格": 680,
    "説明": ""
  },
  {
    "id": "premium_shochu_6",
    "name": "佐藤　黒",
    "カテゴリ": "プレミアム焼酎",
    "価格": 850,
    "説明": ""
  },
  {
    "id": "premium_shochu_7",
    "name": "兼八",
    "カテゴリ": "プレミアム焼酎",
    "価格": 850,
    "説明": ""
  },
  {
    "id": "premium_shochu_8",
    "name": "爆弾ハナタレ",
    "カテゴリ": "プレミアム焼酎",
    "価格": 950,
    "説明": ""
  },
  {
    "id": "premium_shochu_9",
    "name": "百年の孤独",
    "カテゴリ": "プレミアム焼酎",
    "価格": 950,
    "説明": ""
  },
  {
    "id": "premium_shochu_10",
    "name": "魔王",
    "カテゴリ": "プレミアム焼酎",
    "価格": 1100,
    "説明": ""
  },
  {
    "id": "sake_1",
    "name": "日本酒（小）",
    "カテゴリ": "日本酒",
    "価格": 370,
    "説明": ""
  },
  {
    "id": "sake_2",
    "name": "日本酒（大）",
    "カテゴリ": "日本酒",
    "価格": 680,
    "説明": ""
  },
  {
    "id": "sake_3",
    "name": "ふぐひれ酒",
    "カテゴリ": "日本酒",
    "価格": 680,
    "説明": ""
  },
  {
    "id": "sake_4",
    "name": "注ぎ酒",
    "カテゴリ": "日本酒",
    "価格": 370,
    "説明": ""
  },
  {
    "id": "jizake_1",
    "name": "濁し人九平次（愛知）",
    "カテゴリ": "地酒",
    "価格": 880,
    "説明": ""
  },
  {
    "id": "jizake_2",
    "name": "かっぱ（山形）",
    "カテゴリ": "地酒",
    "価格": 580,
    "説明": ""
  },
  {
    "id": "jizake_3",
    "name": "寫楽（福島）",
    "カテゴリ": "地酒",
    "価格": 780,
    "説明": ""
  },
  {
    "id": "jizake_4",
    "name": "来福（茨城）",
    "カテゴリ": "地酒",
    "価格": 780,
    "説明": ""
  },
  {
    "id": "jizake_5",
    "name": "山本（秋田）",
    "カテゴリ": "地酒",
    "価格": 780,
    "説明": ""
  },
  {
    "id": "jizake_6",
    "name": "ばくれん（山形）",
    "カテゴリ": "地酒",
    "価格": 680,
    "説明": ""
  },
  {
    "id": "jizake_7",
    "name": "黒龍（福井）",
    "カテゴリ": "地酒",
    "価格": 580,
    "説明": ""
  },
  {
    "id": "jizake_8",
    "name": "越乃景虎　超辛口（新潟）",
    "カテゴリ": "地酒",
    "価格": 580,
    "説明": ""
  },
  {
    "id": "jizake_9",
    "name": "嬉長　にごり酒（奈良）",
    "カテゴリ": "地酒",
    "価格": 680,
    "説明": ""
  },
  {
    "id": "jizake_10",
    "name": "樽酒",
    "カテゴリ": "地酒",
    "価格": 580,
    "説明": ""
  },
  {
    "id": "highball_1",
    "name": "笑わ家ハイボール（トリハイW）",
    "カテゴリ": "ハイボール",
    "価格": 430,
    "説明": ""
  },
  {
    "id": "highball_2",
    "name": "プレミアムハイボール",
    "カテゴリ": "ハイボール",
    "価格": 480,
    "説明": ""
  },
  {
    "id": "highball_3",
    "name": "バーボンハイボール",
    "カテゴリ": "ハイボール",
    "価格": 480,
    "説明": ""
  },
  {
    "id": "highball_4",
    "name": "下町ハイボール",
    "カテゴリ": "ハイボール",
    "価格": 370,
    "説明": ""
  },
  {
    "id": "highball_5",
    "name": "ジンジャーハイボール",
    "カテゴリ": "ハイボール",
    "価格": 480,
    "説明": ""
  },
  {
    "id": "highball_6",
    "name": "コークハイボール",
    "カテゴリ": "ハイボール",
    "価格": 580,
    "説明": ""
  },
  {
    "id": "cocktail_1",
    "name": "カシスソーダ",
    "カテゴリ": "カクテル",
    "価格": 480,
    "説明": ""
  },
  {
    "id": "cocktail_2",
    "name": "カシスウーロン",
    "カテゴリ": "カクテル",
    "価格": 480,
    "説明": ""
  },
  {
    "id": "cocktail_3",
    "name": "カシスオレンジ",
    "カテゴリ": "カクテル",
    "価格": 480,
    "説明": ""
  },
  {
    "id": "cocktail_4",
    "name": "レッズビール（ビールのトマトジュース割り）",
    "カテゴリ": "カクテル",
    "価格": 580,
    "説明": ""
  },
  {
    "id": "cocktail_5",
    "name": "シャンディガフ",
    "カテゴリ": "カクテル",
    "価格": 580,
    "説明": ""
  },
  {
    "id": "umeshu_1",
    "name": "笑わ家梅酒（ホワイトリカー）",
    "カテゴリ": "梅酒",
    "価格": 530,
    "説明": ""
  },
  {
    "id": "umeshu_2",
    "name": "プレミアム笑わ家梅酒（ブランデー）",
    "カテゴリ": "梅酒",
    "価格": 630,
    "説明": ""
  },
  {
    "id": "umeshu_3",
    "name": "梅酒",
    "カテゴリ": "梅酒",
    "価格": 430,
    "説明": ""
  },
  {
    "id": "umeshu_4",
    "name": "黒糖梅酒",
    "カテゴリ": "梅酒",
    "価格": 580,
    "説明": ""
  },
  {
    "id": "umeshu_5",
    "name": "ゆず梅酒",
    "カテゴリ": "梅酒",
    "価格": 580,
    "説明": ""
  },
  {
    "id": "umeshu_6",
    "name": "はっさく梅酒",
    "カテゴリ": "梅酒",
    "価格": 580,
    "説明": ""
  },
  {
    "id": "wine_1",
    "name": "グラスワイン",
    "カテゴリ": "ワイン",
    "価格": 430,
    "説明": ""
  },
  {
    "id": "wine_2",
    "name": "フルボトル",
    "カテゴリ": "ワイン",
    "価格": 2400,
    "説明": ""
  },
  {
    "id": "whisky_1",
    "name": "ウイスキーS",
    "カテゴリ": "ウイスキー",
    "価格": 460,
    "説明": ""
  },
  {
    "id": "whisky_2",
    "name": "ウイスキーW　日本（角、岩井）",
    "カテゴリ": "ウイスキー",
    "価格": 850,
    "説明": ""
  },
  {
    "id": "whisky_3",
    "name": "バーボンS",
    "カテゴリ": "ウイスキー",
    "価格": 460,
    "説明": ""
  },
  {
    "id": "whisky_4",
    "name": "バーボンW",
    "カテゴリ": "ウイスキー",
    "価格": 850,
    "説明": ""
  },
  {
    "id": "other_1",
    "name": "デンキブラン",
    "カテゴリ": "その他",
    "価格": 370,
    "説明": ""
  },
  {
    "id": "other_2",
    "name": "梅割り",
    "カテゴリ": "その他",
    "価格": 290,
    "説明": ""
  },
  {
    "id": "bottle_1",
    "name": "飲みきり",
    "カテゴリ": "ボトル",
    "価格": 1400,
    "説明": ""
  },
  {
    "id": "bottle_2",
    "name": "甲",
    "カテゴリ": "ボトル",
    "価格": 1900,
    "説明": ""
  },
  {
    "id": "bottle_3",
    "name": "米",
    "カテゴリ": "ボトル",
    "価格": 2900,
    "説明": ""
  },
  {
    "id": "bottle_4",
    "name": "麦",
    "カテゴリ": "ボトル",
    "価格": 2900,
    "説明": ""
  },
  {
    "id": "bottle_5",
    "name": "芋",
    "カテゴリ": "ボトル",
    "価格": 2900,
    "説明": ""
  },
  {
    "id": "bottle_6",
    "name": "き六",
    "カテゴリ": "ボトル",
    "価格": 3400,
    "説明": ""
  },
  {
    "id": "bottle_7",
    "name": "中々",
    "カテゴリ": "ボトル",
    "価格": 3400,
    "説明": ""
  },
  {
    "id": "bottle_8",
    "name": "三岳",
    "カテゴリ": "ボトル",
    "価格": 3400,
    "説明": ""
  },
  {
    "id": "bottle_9",
    "name": "赤霧島",
    "カテゴリ": "ボトル",
    "価格": 3400,
    "説明": ""
  },
  {
    "id": "bottle_10",
    "name": "川越",
    "カテゴリ": "ボトル",
    "価格": 3800,
    "説明": ""
  },
  {
    "id": "bottle_11",
    "name": "富乃宝山",
    "カテゴリ": "ボトル",
    "価格": 3800,
    "説明": ""
  },
  {
    "id": "bottle_12",
    "name": "吉兆宝山",
    "カテゴリ": "ボトル",
    "価格": 3800,
    "説明": ""
  },
  {
    "id": "bottle_option_1",
    "name": "アイス",
    "カテゴリ": "ボトルのお供",
    "価格": 100,
    "説明": ""
  },
  {
    "id": "bottle_option_2",
    "name": "お湯",
    "カテゴリ": "ボトルのお供",
    "価格": 200,
    "説明": ""
  },
  {
    "id": "bottle_option_3",
    "name": "ミネラルウォーター",
    "カテゴリ": "ボトルのお供",
    "価格": 230,
    "説明": ""
  },
  {
    "id": "bottle_option_4",
    "name": "ウーロン茶（デキャンタ）",
    "カテゴリ": "ボトルのお供",
    "価格": 400,
    "説明": ""
  },
  {
    "id": "bottle_option_5",
    "name": "濃い緑茶（デキャンタ）",
    "カテゴリ": "ボトルのお供",
    "価格": 580,
    "説明": ""
  },
  {
    "id": "bottle_option_6",
    "name": "炭酸水",
    "カテゴリ": "ボトルのお供",
    "価格": 300,
    "説明": ""
  },
  {
    "id": "bottle_option_7",
    "name": "梅干",
    "カテゴリ": "ボトルのお供",
    "価格": 100,
    "説明": ""
  },
  {
    "id": "bottle_option_8",
    "name": "レモンスライス",
    "カテゴリ": "ボトルのお供",
    "価格": 50,
    "説明": ""
  },
  {
    "id": "chaser_1",
    "name": "コカコーラ",
    "カテゴリ": "チェイサー",
    "価格": 240,
    "説明": ""
  },
  {
    "id": "chaser_2",
    "name": "ジンジャーエール",
    "カテゴリ": "チェイサー",
    "価格": 240,
    "説明": ""
  },
  {
    "id": "chaser_3",
    "name": "ウーロン茶（デキャンタ）",
    "カテゴリ": "チェイサー",
    "価格": 240,
    "説明": ""
  },
  {
    "id": "chaser_4",
    "name": "濃い緑茶（デキャンタ）",
    "カテゴリ": "チェイサー",
    "価格": 240,
    "説明": ""
  },
  {
    "id": "chaser_5",
    "name": "オレンジジュース",
    "カテゴリ": "チェイサー",
    "価格": 240,
    "説明": ""
  },
  {
    "id": "chaser_6",
    "name": "トマトジュース",
    "カテゴリ": "チェイサー",
    "価格": 280,
    "説明": ""
  },
  {
    "id": "kushiyaki_pork_1",
    "name": "かしら",
    "カテゴリ": "炭火串焼き（豚肉）",
    "価格": 130,
    "説明": ""
  },
  {
    "id": "kushiyaki_pork_2",
    "name": "たん",
    "カテゴリ": "炭火串焼き（豚肉）",
    "価格": 130,
    "説明": ""
  },
  {
    "id": "kushiyaki_pork_3",
    "name": "ハラミ",
    "カテゴリ": "炭火串焼き（豚肉）",
    "価格": 130,
    "説明": ""
  },
  {
    "id": "kushiyaki_pork_4",
    "name": "なんこつ",
    "カテゴリ": "炭火串焼き（豚肉）",
    "価格": 130,
    "説明": ""
  },
  {
    "id": "kushiyaki_pork_5",
    "name": "はつ",
    "カテゴリ": "炭火串焼き（豚肉）",
    "価格": 130,
    "説明": ""
  },
  {
    "id": "kushiyaki_pork_6",
    "name": "レバー",
    "カテゴリ": "炭火串焼き（豚肉）",
    "価格": 130,
    "説明": ""
  },
  {
    "id": "kushiyaki_pork_7",
    "name": "しろ",
    "カテゴリ": "炭火串焼き（豚肉）",
    "価格": 130,
    "説明": ""
  },
  {
    "id": "kushiyaki_pork_8",
    "name": "テッポウ",
    "カテゴリ": "炭火串焼き（豚肉）",
    "価格": 130,
    "説明": ""
  },
  {
    "id": "kushiyaki_pork_9",
    "name": "バラ",
    "カテゴリ": "炭火串焼き（豚肉）",
    "価格": 130,
    "説明": ""
  },
  {
    "id": "kushiyaki_pork_10",
    "name": "キクアブラ",
    "カテゴリ": "炭火串焼き（豚肉）",
    "価格": 130,
    "説明": ""
  },
  {
    "id": "kushiyaki_pork_11",
    "name": "おまかせ5本セット",
    "カテゴリ": "炭火串焼き（豚肉）",
    "価格": 630,
    "説明": ""
  },
  {
    "id": "kushiyaki_chicken_1",
    "name": "もも",
    "カテゴリ": "炭火串焼き（鶏肉）",
    "価格": 140,
    "説明": ""
  },
  {
    "id": "kushiyaki_chicken_2",
    "name": "ねぎま",
    "カテゴリ": "炭火串焼き（鶏肉）",
    "価格": 140,
    "説明": ""
  },
  {
    "id": "kushiyaki_chicken_3",
    "name": "皮",
    "カテゴリ": "炭火串焼き（鶏肉）",
    "価格": 140,
    "説明": ""
  },
  {
    "id": "kushiyaki_chicken_4",
    "name": "砂肝",
    "カテゴリ": "炭火串焼き（鶏肉）",
    "価格": 140,
    "説明": ""
  },
  {
    "id": "kushiyaki_chicken_5",
    "name": "ぼんじり",
    "カテゴリ": "炭火串焼き（鶏肉）",
    "価格": 140,
    "説明": ""
  },
  {
    "id": "kushiyaki_chicken_6",
    "name": "皮にんにく",
    "カテゴリ": "炭火串焼き（鶏肉）",
    "価格": 140,
    "説明": ""
  },
  {
    "id": "kushiyaki_chicken_7",
    "name": "手羽先",
    "カテゴリ": "炭火串焼き（鶏肉）",
    "価格": 140,
    "説明": ""
  },
  {
    "id": "kushiyaki_chicken_8",
    "name": "せせり",
    "カテゴリ": "炭火串焼き（鶏肉）",
    "価格": 160,
    "説明": ""
  },
  {
    "id": "kushiyaki_chicken_9",
    "name": "アミレバー",
    "カテゴリ": "炭火串焼き（鶏肉）",
    "価格": 190,
    "説明": ""
  },
  {
    "id": "kushiyaki_chicken_10",
    "name": "アミハツ",
    "カテゴリ": "炭火串焼き（鶏肉）",
    "価格": 190,
    "説明": ""
  },
  {
    "id": "kushiyaki_chicken_11",
    "name": "アミササミ",
    "カテゴリ": "炭火串焼き（鶏肉）",
    "価格": 190,
    "説明": ""
  },
  {
    "id": "kushiyaki_chicken_12",
    "name": "つくね",
    "カテゴリ": "炭火串焼き（鶏肉）",
    "価格": 190,
    "説明": ""
  },
  {
    "id": "kushiyaki_chicken_13",
    "name": "牛すじ",
    "カテゴリ": "炭火串焼き（鶏肉）",
    "価格": 190,
    "説明": ""
  },
  {
    "id": "kushiyaki_vegetable_1",
    "name": "しいたけ",
    "カテゴリ": "野菜串焼き",
    "価格": 140,
    "説明": ""
  },
  {
    "id": "kushiyaki_vegetable_2",
    "name": "ししとう",
    "カテゴリ": "野菜串焼き",
    "価格": 140,
    "説明": ""
  },
  {
    "id": "kushiyaki_vegetable_3",
    "name": "深谷ネギ",
    "カテゴリ": "野菜串焼き",
    "価格": 140,
    "説明": ""
  },
  {
    "id": "kushiyaki_unagi_1",
    "name": "鰻 焼柵串",
    "カテゴリ": "うなぎ串焼き",
    "価格": 340,
    "説明": ""
  },
  {
    "id": "kushiyaki_unagi_2",
    "name": "鰻肝",
    "カテゴリ": "うなぎ串焼き",
    "価格": 240,
    "説明": ""
  },
  {
    "id": "yakimono_1",
    "name": "ローストポーク",
    "カテゴリ": "焼き物",
    "価格": 530,
    "説明": ""
  },
  {
    "id": "yakimono_2",
    "name": "トントロ焼き",
    "カテゴリ": "焼き物",
    "価格": 480,
    "説明": ""
  },
  {
    "id": "yakimono_3",
    "name": "揚げたて厚揚げ",
    "カテゴリ": "焼き物",
    "価格": 430,
    "説明": ""
  },
  {
    "id": "yakimono_4",
    "name": "えいひれ",
    "カテゴリ": "焼き物",
    "価格": 400,
    "説明": ""
  },
  {
    "id": "yakimono_5",
    "name": "丸干しイカ（わた入り）",
    "カテゴリ": "焼き物",
    "価格": 580,
    "説明": ""
  },
  {
    "id": "yakimono_6",
    "name": "にんにく揚げ",
    "カテゴリ": "焼き物",
    "価格": 370,
    "説明": ""
  },
  {
    "id": "yakimono_7",
    "name": "山芋ステーキ",
    "カテゴリ": "焼き物",
    "価格": 480,
    "説明": ""
  },
  {
    "id": "yakimono_8",
    "name": "腸詰めフランク",
    "カテゴリ": "焼き物",
    "価格": 400,
    "説明": ""
  },
  {
    "id": "yakimono_9",
    "name": "炭焼き厚切りベーコン",
    "カテゴリ": "焼き物",
    "価格": 430,
    "説明": ""
  },
  {
    "id": "yakimono_10",
    "name": "焼きたて 玉子焼き",
    "カテゴリ": "焼き物",
    "価格": 430,
    "説明": ""
  },
  {
    "id": "shime_1",
    "name": "焼きおにぎり",
    "カテゴリ": "しめ",
    "価格": 400,
    "説明": ""
  },
  {
    "id": "shime_2",
    "name": "川越太麺やきそば",
    "カテゴリ": "しめ",
    "価格": 530,
    "説明": ""
  },
  {
    "id": "shime_3",
    "name": "カレーうどん",
    "カテゴリ": "しめ",
    "価格": 530,
    "説明": ""
  },
  {
    "id": "shime_4",
    "name": "スパイシーカレー雑炊",
    "カテゴリ": "しめ",
    "価格": 630,
    "説明": ""
  },
  {
    "id": "ippin_1",
    "name": "ポテトサラダ",
    "カテゴリ": "一品料理",
    "価格": 370,
    "説明": ""
  },
  {
    "id": "ippin_2",
    "name": "丸ごと玉ねぎおかかポン酢",
    "カテゴリ": "一品料理",
    "価格": 370,
    "説明": ""
  },
  {
    "id": "ippin_3",
    "name": "たこわさび",
    "カテゴリ": "一品料理",
    "価格": 300,
    "説明": ""
  },
  {
    "id": "ippin_4",
    "name": "元祖 梅にんにく",
    "カテゴリ": "一品料理",
    "価格": 300,
    "説明": ""
  },
  {
    "id": "ippin_5",
    "name": "冷奴",
    "カテゴリ": "一品料理",
    "価格": 340,
    "説明": ""
  },
  {
    "id": "ippin_6",
    "name": "湯豆腐 関西風",
    "カテゴリ": "一品料理",
    "価格": 430,
    "説明": ""
  },
  {
    "id": "ippin_7",
    "name": "湯豆腐 関東風",
    "カテゴリ": "一品料理",
    "価格": 370,
    "説明": ""
  },
  {
    "id": "ippin_8",
    "name": "茶豆",
    "カテゴリ": "一品料理",
    "価格": 340,
    "説明": ""
  },
  {
    "id": "ippin_9",
    "name": "焼き茶豆",
    "カテゴリ": "一品料理",
    "価格": 370,
    "説明": ""
  },
  {
    "id": "ippin_10",
    "name": "バリバリキャベツ",
    "カテゴリ": "一品料理",
    "価格": 300,
    "説明": ""
  },
  {
    "id": "ippin_11",
    "name": "きゅうりのたたき",
    "カテゴリ": "一品料理",
    "価格": 370,
    "説明": ""
  },
  {
    "id": "ippin_12",
    "name": "きゅうりのたたき（ガツ入り）",
    "カテゴリ": "一品料理",
    "価格": 460,
    "説明": ""
  },
  {
    "id": "ippin_13",
    "name": "冷やしトマト",
    "カテゴリ": "一品料理",
    "価格": 370,
    "説明": ""
  },
  {
    "id": "ippin_14",
    "name": "みそきゅう",
    "カテゴリ": "一品料理",
    "価格": 300,
    "説明": ""
  },
  {
    "id": "ippin_15",
    "name": "オニオンスライス",
    "カテゴリ": "一品料理",
    "価格": 300,
    "説明": ""
  },
  {
    "id": "ippin_16",
    "name": "お新香 盛り合わせ",
    "カテゴリ": "一品料理",
    "価格": 370,
    "説明": ""
  },
  {
    "id": "ippin_17",
    "name": "キムチ",
    "カテゴリ": "一品料理",
    "価格": 300,
    "説明": ""
  },
  {
    "id": "ippin_18",
    "name": "じゃがバター",
    "カテゴリ": "一品料理",
    "価格": 400,
    "説明": ""
  },
  {
    "id": "ippin_19",
    "name": "コーンバター",
    "カテゴリ": "一品料理",
    "価格": 370,
    "説明": ""
  },
  {
    "id": "ippin_20",
    "name": "ニラレバー炒め",
    "カテゴリ": "一品料理",
    "価格": 580,
    "説明": ""
  },
  {
    "id": "nikomi_1",
    "name": "豚モツ煮込み",
    "カテゴリ": "煮込み",
    "価格": 430,
    "説明": ""
  },
  {
    "id": "sashi_1",
    "name": "レバテキ",
    "カテゴリ": "刺し",
    "価格": 530,
    "説明": ""
  },
  {
    "id": "sashi_2",
    "name": "ガツ差し",
    "カテゴリ": "刺し",
    "価格": 370,
    "説明": ""
  },
  {
    "id": "agemono_1",
    "name": "ポテトフライ",
    "カテゴリ": "揚げ物",
    "価格": 300,
    "説明": ""
  },
  {
    "id": "agemono_2",
    "name": "伝説の大きい鶏唐揚げ",
    "カテゴリ": "揚げ物",
    "価格": 460,
    "説明": ""
  },
  {
    "id": "agemono_3",
    "name": "鶏なんこつ揚げ",
    "カテゴリ": "揚げ物",
    "価格": 460,
    "説明": ""
  },
  {
    "id": "agemono_4",
    "name": "とり皮餃子揚げ",
    "カテゴリ": "揚げ物",
    "価格": 370,
    "説明": ""
  },
  {
    "id": "agemono_5",
    "name": "さつま揚げ",
    "カテゴリ": "揚げ物",
    "価格": 370,
    "説明": ""
  },
  {
    "id": "agemono_6",
    "name": "あじフライ",
    "カテゴリ": "揚げ物",
    "価格": 430,
    "説明": ""
  },
  {
    "id": "agemono_7",
    "name": "揚げなす",
    "カテゴリ": "揚げ物",
    "価格": 370,
    "説明": ""
  },
  {
    "id": "yakizakana_1",
    "name": "新さんま塩焼き",
    "カテゴリ": "焼き魚",
    "価格": 580,
    "説明": ""
  },
  {
    "id": "yakizakana_2",
    "name": "ホッケ",
    "カテゴリ": "焼き魚",
    "価格": 580,
    "説明": ""
  },
  {
    "id": "yakizakana_3",
    "name": "サバ文化干し",
    "カテゴリ": "焼き魚",
    "価格": 460,
    "説明": ""
  },
  {
    "id": "yakizakana_4",
    "name": "はたはた一夜干し",
    "カテゴリ": "焼き魚",
    "価格": 370,
    "説明": ""
  }
]